AUTHORS
Changelog
INSTALL
LICENSE
MANIFEST.in
README
README.rst
THANKS
TODO
setup.cfg
setup.py
doc/.DS_Store
doc/Makefile
doc/source/.DS_Store
doc/source/conf.py
doc/source/couchdb.rst
doc/source/develop.rst
doc/source/flatty.rst
doc/source/index.rst
doc/source/introduction.rst
doc/source/_static/.hidden
doc/source/_static/images/.DS_Store
src/flatty/__init__.py
src/flatty/couch.py
src/flatty/flatty.py
src/flatty/mongo.py
src/flatty.egg-info/PKG-INFO
src/flatty.egg-info/SOURCES.txt
src/flatty.egg-info/dependency_links.txt
src/flatty.egg-info/top_level.txt
src/flatty.egg-info/zip-safe
src/flatty/tests/__init__.py
src/flatty/tests/dummy.py
src/flatty/tests/test_actions.py
src/flatty/tests/test_couchdb.py
src/flatty/tests/test_mongodb.py
src/flatty/tests/test_utils.py