Metadata-Version: 1.0
Name: flatty
Version: 0.1.2
Summary: flatty - marshaller/unmarshaller for light-schema python objects
Home-page: http://packages.python.org/flatty
Author: Christian Haintz
Author-email: christian.haintz@orangelabs.at
License: BSD
Keywords: marshaller schema objectmapper couchdb mongodb orm
Platform: any
Classifier: Development Status :: 3 - Alpha
Classifier: Operating System :: OS Independent
Classifier: Programming Language :: Python
Classifier: License :: OSI Approved :: BSD License
Classifier: Intended Audience :: Developers
Classifier: Topic :: Software Development :: Pre-processors
Classifier: Topic :: Software Development :: Libraries :: Python Modules
